ismalab2/__init__.py
ismalab2/module.py
ismalab2-0.0.1.dist-info/LICENSE
ismalab2-0.0.1.dist-info/METADATA
ismalab2-0.0.1.dist-info/WHEEL
ismalab2-0.0.1.dist-info/top_level.txt
ismalab2-0.0.1.dist-info/RECORD
